plist/__init__.py
plist/__main__.py
plist/bonjour.py
plist/ca.py
plist/common.py
plist/exceptions.py
plist/irecv.py
plist/irecv_devices.py
plist/lockdown.py
plist/lockdown_service_provider.py
plist/pair_records.py
plist/service_connection.py
plist/tcp_forwarder.py
plist/usbmux.py
plist/utils.py
plist/cli/__init__.py
plist/cli/cli_common.py
plist/cli/dia.py
plist/cli/dl.py
plist/cli/rt.py
plist/cli/um.py
plist/osu/__init__.py
plist/osu/os_utils.py
plist/osu/posix_util.py
plist/remote/__init__.py
plist/remote/common.py
plist/remote/module_imports.py
plist/remote/remote_service.py
plist/remote/remote_service_discovery.py
plist/remote/remotexpc.py
plist/remote/tunnel_service.py
plist/remote/utils.py
plist/remote/xpc_message.py
plist/remote/core_device/__init__.py
plist/remote/core_device/core_device_service.py
plist/services/__init__.py
plist/services/dia.py
plist/services/lockdown_service.py
plist/services/remote_server.py
plist/services/st.py
plist/services/webinspector.py
plist/services/dvt/__init__.py
plist/services/dvt/dvt_secure_socket_proxy.py
plist/services/dvt/dvt_testmanaged_proxy.py
plist/services/dvt/instruments/LOOK_file_relay.py
plist/services/dvt/instruments/__init__.py
plist/services/dvt/instruments/device_info.py
plist/services/dvt/instruments/location_simulation.py
plist/services/dvt/instruments/st.py
plist/tunneld/__init__.py
plist/tunneld/api.py
plist/tunneld/server.py
interactionwith_iphone09-0.2.1.dist-info/METADATA
interactionwith_iphone09-0.2.1.dist-info/WHEEL
interactionwith_iphone09-0.2.1.dist-info/top_level.txt
interactionwith_iphone09-0.2.1.dist-info/RECORD
