Metadata-Version: 2.4
Name: interactionWith_iPhone09
Version: 0.2.1
Author-email: Eduard <oleksey.21.05.2000@gmail.com>
Requires-Python: >=3.7
Requires-Dist: aiofiles
Requires-Dist: annotated_types
Requires-Dist: anyio
Requires-Dist: apple_compress
Requires-Dist: asn1
Requires-Dist: asttokens
Requires-Dist: blessed
Requires-Dist: certifi
Requires-Dist: cffi
Requires-Dist: charset_normalizer
Requires-Dist: Crypto
Requires-Dist: cryptography
Requires-Dist: dateutil
Requires-Dist: decorator
Requires-Dist: dns
Requires-Dist: dotenv
Requires-Dist: editor
Requires-Dist: email_validator
Requires-Dist: enum_compat
Requires-Dist: exceptiongroup
Requires-Dist: executing
Requires-Dist: h11
Requires-Dist: httpcore
Requires-Dist: httptools
Requires-Dist: httpx
Requires-Dist: humanfriendly
Requires-Dist: idna
Requires-Dist: IPython
Requires-Dist: itsdangerous
Requires-Dist: jedi
Requires-Dist: jinja2
Requires-Dist: la_panic
Requires-Dist: loguru
Requires-Dist: markdown_it
Requires-Dist: markupsafe
Requires-Dist: matplotlib_inline
Requires-Dist: mdurl
Requires-Dist: multipart
Requires-Dist: orjson
Requires-Dist: parso
Requires-Dist: pexpect
Requires-Dist: ptyprocess
Requires-Dist: pure_eval
Requires-Dist: pycparser
Requires-Dist: pydantic
Requires-Dist: pydantic_core
Requires-Dist: pydantic_extra_types
Requires-Dist: pydantic_settings
Requires-Dist: pylzss
Requires-Dist: python_dateutil
Requires-Dist: python_dotenv
Requires-Dist: python_multipart
Requires-Dist: python_pcapng
Requires-Dist: pytun_pmd3
Requires-Dist: readchar
Requires-Dist: rich
Requires-Dist: rich_toolkit
Requires-Dist: runs
Requires-Dist: rust
Requires-Dist: shellingham
Requires-Dist: sniffio
Requires-Dist: stack_data
Requires-Dist: termcolor
Requires-Dist: traitlets
Requires-Dist: typer
Requires-Dist: types_python_dateutil
Requires-Dist: typing_extensions
Requires-Dist: typing_inspection
Requires-Dist: ujson
Requires-Dist: urllib3
Requires-Dist: usb
Requires-Dist: uvloop
Requires-Dist: watchfiles
Requires-Dist: wcwidth
Requires-Dist: websockets
Requires-Dist: xmod
Requires-Dist: xompletions
Requires-Dist: xontrib
Requires-Dist: yaml
Requires-Dist: construct>=2.9.29
Requires-Dist: click
Requires-Dist: coloredlogs
Requires-Dist: bpylist2>=4.0.1
Requires-Dist: pygments
Requires-Dist: hexdump
Requires-Dist: arrow
Requires-Dist: daemonize
Requires-Dist: gpxpy<1.6.0
Requires-Dist: pykdebugparser>=1.2.7
Requires-Dist: pyusb>=1.2.1
Requires-Dist: tqdm
Requires-Dist: requests
Requires-Dist: xonsh
Requires-Dist: parameter_decorators
Requires-Dist: packaging
Requires-Dist: pygnuutils>=0.0.7
Requires-Dist: cryptography>=41.0.1
Requires-Dist: pycrashreport>=1.2.4
Requires-Dist: fastapi[all]>=0.93.0
Requires-Dist: uvicorn>=0.15.0
Requires-Dist: starlette
Requires-Dist: wsproto
Requires-Dist: nest_asyncio>=1.5.5
Requires-Dist: Pillow
Requires-Dist: inquirer3>=0.6.0
Requires-Dist: ipsw_parser>=1.3.4
Requires-Dist: remotezip2
Requires-Dist: zeroconf>=0.132.2
Requires-Dist: ifaddr
Requires-Dist: hyperframe
Requires-Dist: srptools
Requires-Dist: qh3<2,>=1.0.0
Requires-Dist: developer_disk_image>=0.0.2
Requires-Dist: opack2
Requires-Dist: psutil
Requires-Dist: pytun-pmd3>=2.2.2
Requires-Dist: prompt_toolkit
Requires-Dist: sslpsk-pmd3>=1.0.3; python_version < "3.13"
Requires-Dist: python-pcapng>=2.1.1
Requires-Dist: plumbum
Requires-Dist: pyimg4>=0.8.8
Requires-Dist: aiofiles
